simplecfg/__init__.py
simplecfg/config.py
simplecfg/dir.py
simplecfg-1.0.dist-info/LICENSE
simplecfg-1.0.dist-info/METADATA
simplecfg-1.0.dist-info/WHEEL
simplecfg-1.0.dist-info/top_level.txt
simplecfg-1.0.dist-info/RECORD
