Metadata-Version: 2.1
Name: simplecfg
Version: 1.0
Summary: A library to easily manage program configuration.
Home-page: https://github.com/itsmaxymoo/simplecfg
Author: Max Loiacono
Author-email: 
License: Mozilla Public License version 2.0
Platform: UNKNOWN
Classifier: Programming Language :: Python :: 3
Classifier: License :: OSI Approved :: Mozilla Public License 2.0 (MPL 2.0)
Classifier: Operating System :: OS Independent
Requires-Python: >=3.3
